pyarmor/mini/pyarmor_mini.so
pyarmor_mini-3.0.dist-info/METADATA
pyarmor_mini-3.0.dist-info/WHEEL
pyarmor_mini-3.0.dist-info/top_level.txt
pyarmor_mini-3.0.dist-info/RECORD
